caipiao/__init__.py
caipiao-1.0.0.dist-info/METADATA
caipiao-1.0.0.dist-info/WHEEL
caipiao-1.0.0.dist-info/top_level.txt
caipiao-1.0.0.dist-info/RECORD
