Metadata-Version: 2.1
Name: caipiao
Version: 1.0.0
Summary: A caipiao.
Home-page: UNKNOWN
Author: ch_lgp
Author-email: 1158200486@qq.com
License: MIT
Keywords: caipiao
Platform: UNKNOWN
